README.txt
__init__.py
bootstrap.py
buildout.cfg
plone.cfg
setup.cfg
setup.py
dist/shop.vitrine-1.0.zip
docs/HISTORY.txt
docs/INSTALL.txt
docs/LICENSE.GPL
docs/LICENSE.txt
shop/__init__.py
shop.vitrine.egg-info/PKG-INFO
shop.vitrine.egg-info/SOURCES.txt
shop.vitrine.egg-info/dependency_links.txt
shop.vitrine.egg-info/entry_points.txt
shop.vitrine.egg-info/namespace_packages.txt
shop.vitrine.egg-info/not-zip-safe
shop.vitrine.egg-info/paster_plugins.txt
shop.vitrine.egg-info/requires.txt
shop.vitrine.egg-info/top_level.txt
shop/vitrine/Categoria.txt
shop/vitrine/INTEGRATION.txt
shop/vitrine/Produto.txt
shop/vitrine/Size.txt
shop/vitrine/__init__.py
shop/vitrine/categoria.py
shop/vitrine/configure.zcml
shop/vitrine/produto.py
shop/vitrine/produto.xml
shop/vitrine/size.py
shop/vitrine/tests.py
shop/vitrine/categoria_templates/sampleview.pt
shop/vitrine/locales/README.txt
shop/vitrine/models/categoria.xml
shop/vitrine/models/produto.xml
shop/vitrine/models/size.xml
shop/vitrine/produto_templates/view.pt
shop/vitrine/profiles/default/metadata.xml
shop/vitrine/profiles/default/types.xml
shop/vitrine/profiles/default/types/shop.vitrine.categoria.xml
shop/vitrine/profiles/default/types/shop.vitrine.produto.xml
shop/vitrine/profiles/default/types/shop.vitrine.size.xml
shop/vitrine/resources/README.txt
shop/vitrine/size_templates/sampleview.pt