Metadata-Version: 1.1
Name: shop.vitrine
Version: 1.0
Summary: Shop Vitrine
Home-page: http://svn.plone.org/svn/collective/
Author: Webtec Solucoes Inteligentes
Author-email: webtecsi@yahoo.com.br
License: GPL
Platform: UNKNOWN
Classifier: Framework :: Plone
Classifier: Programming Language :: Python
Classifier: Topic :: Software Development :: Libraries :: Python Modules
